bottle_jade.py
bottle_jade-0.2.1.dist-info/DESCRIPTION.rst
bottle_jade-0.2.1.dist-info/METADATA
bottle_jade-0.2.1.dist-info/metadata.json
bottle_jade-0.2.1.dist-info/RECORD
bottle_jade-0.2.1.dist-info/top_level.txt
bottle_jade-0.2.1.dist-info/WHEEL
