Metadata-Version: 2.0
Name: bottle-jade
Version: 0.2.1
Summary: UNKNOWN
Home-page: https://github.com/klen/bottle-jade
Author: Kirill Klenov
Author-email: horneds@gmail.com
License: MIT
Keywords: bottle,jade
Platform: Any
Classifier: Development Status :: 4 - Beta
Classifier: Intended Audience :: Developers
Classifier: License :: OSI Approved :: BSD License
Classifier: Natural Language :: English
Classifier: Natural Language :: Russian
Classifier: Operating System :: OS Independent
Classifier: Programming Language :: Python :: 2
Classifier: Programming Language :: Python :: 3
Classifier: Programming Language :: Python
Classifier: Topic :: Software Development :: Libraries :: Python Modules
Classifier: Topic :: Software Development :: Testing
Classifier: Topic :: Utilities
Requires-Dist: bottle
Requires-Dist: pyjade
